{"USD": {"name": "US Dollar", "sell": 59600, "buy": 59500}, "EUR": {"name": "Euro", "sell": 64250, "buy": 64150}, "GBP": {"name": "British Pound", "sell": 74650, "buy": 74450}, "CHF": {"name": "Swiss Franc", "sell": 65750, "buy": 65650}, "CAD": {"name": "Canadian Dollar", "sell": 43600, "buy": 43500}, "AUD": {"name": "Australian Dollar", "sell": 39350, "buy": 39250}, "SEK": {"name": "Swedish Krona", "sell": 5485, "buy": 5470}, "NOK": {"name": "Norwegian Krone", "sell": 5485, "buy": 5470}, "RUB": {"name": "Russian Ruble", "sell": 650, "buy": 645}, "THB": {"name": "Thai Baht", "sell": 1620, "buy": 1615}, "SGD": {"name": "Singapore Dollar", "sell": 44000, "buy": 43900}, "HKD": {"name": "Hong Kong Dollar", "sell": 7630, "buy": 7600}, "AZN": {"name": "Azerbaijani Manat", "sell": 35100, "buy": 35000}, "AMD": {"name": "10 Armenian Dram", "sell": 1535, "buy": 1530}, "DKK": {"name": "Danish Krone", "sell": 8610, "buy": 8590}, "AED": {"name": "UAE Dirham", "sell": 16160, "buy": 16120}, "JPY": {"name": "10 Japanese Yen", "sell": 3825, "buy": 3815}, "TRY": {"name": "Turkish Lira", "sell": 1850, "buy": 1830}, "CNY": {"name": "Chinese Yuan", "sell": 8240, "buy": 8220}, "SAR": {"name": "Saudi Riyal", "sell": 15900, "buy": 15800}, "INR": {"name": "Indian Rupee", "sell": 715, "buy": 710}, "MYR": {"name": "Malaysian Ringgit", "sell": 12550, "buy": 12450}, "AFN": {"name": "Afghan Afghani", "sell": 825, "buy": 820}, "KWD": {"name": "Kuwaiti Dinar", "sell": 193800, "buy": 193400}, "IQD": {"name": "100 Iraqi Dinar", "sell": 4545, "buy": 4535}, "BHD": {"name": "Bahraini Dinar", "sell": 158150, "buy": 157650}, "OMR": {"name": "Omani Rial", "sell": 154850, "buy": 154550}, "QAR": {"name": "Qatari Rial", "sell": 16350, "buy": 16250}, "emami1": {"name": "Emami", "sell": 40600000, "buy": 40100000}, "azadi1g": {"name": "Gerami", "sell": 6600000, "buy": 6100000}, "azadi1": {"name": "Azadi", "sell": 37600000, "buy": 37000000}, "azadi1_2": {"name": "½ Azadi", "sell": 23500000, "buy": 22900000}, "azadi1_4": {"name": "¼ Azadi", "sell": 14900000, "buy": 14400000}, "mithqal": {"name": "Gold Mithqal", "price": 14465000}, "gol18": {"name": "Gold Gram", "price": 3339258}, "ounce": {"name": "Ounce", "price": 2339.97}, "bitcoin": {"name": "Bitcoin", "price": 63097.28}}
