{"USD": {"name": "US Dollar", "sell": 53100, "buy": 53000}, "EUR": {"name": "Euro", "sell": 58000, "buy": 57900}, "GBP": {"name": "British Pound", "sell": 67300, "buy": 67100}, "CHF": {"name": "Swiss Franc", "sell": 61800, "buy": 61700}, "CAD": {"name": "Canadian Dollar", "sell": 39400, "buy": 39300}, "AUD": {"name": "Australian Dollar", "sell": 35150, "buy": 35050}, "SEK": {"name": "Swedish Krona", "sell": 5120, "buy": 5105}, "NOK": {"name": "Norwegian Krone", "sell": 5100, "buy": 5085}, "RUB": {"name": "Russian Ruble", "sell": 605, "buy": 600}, "THB": {"name": "Thai Baht", "sell": 1510, "buy": 1505}, "SGD": {"name": "Singapore Dollar", "sell": 39700, "buy": 39600}, "HKD": {"name": "Hong Kong Dollar", "sell": 6790, "buy": 6760}, "AZN": {"name": "Azerbaijani Manat", "sell": 31200, "buy": 31100}, "AMD": {"name": "10 Armenian Dram", "sell": 1310, "buy": 1305}, "DKK": {"name": "Danish Krone", "sell": 7770, "buy": 7750}, "AED": {"name": "UAE Dirham", "sell": 14630, "buy": 14580}, "JPY": {"name": "10 Japanese Yen", "sell": 3635, "buy": 3625}, "TRY": {"name": "Turkish Lira", "sell": 1765, "buy": 1745}, "CNY": {"name": "Chinese Yuan", "sell": 7465, "buy": 7445}, "SAR": {"name": "Saudi Riyal", "sell": 14150, "buy": 14050}, "INR": {"name": "Indian Rupee", "sell": 640, "buy": 635}, "MYR": {"name": "Malaysian Ringgit", "sell": 11350, "buy": 11250}, "AFN": {"name": "Afghan Afghani", "sell": 745, "buy": 740}, "KWD": {"name": "Kuwaiti Dinar", "sell": 172750, "buy": 172350}, "IQD": {"name": "100 Iraqi Dinar", "sell": 4045, "buy": 4035}, "BHD": {"name": "Bahraini Dinar", "sell": 140850, "buy": 140350}, "OMR": {"name": "Omani Rial", "sell": 137950, "buy": 137650}, "QAR": {"name": "Qatari Rial", "sell": 14600, "buy": 14500}, "emami1": {"name": "Emami", "sell": 31700000, "buy": 31200000}, "azadi1g": {"name": "Gerami", "sell": 6100000, "buy": 5700000}, "azadi1": {"name": "Azadi", "sell": 28500000, "buy": 28000000}, "azadi1_2": {"name": "½ Azadi", "sell": 18000000, "buy": 17500000}, "azadi1_4": {"name": "¼ Azadi", "sell": 11000000, "buy": 10500000}, "mithqal": {"name": "Gold Mithqal", "price": 11586000}, "gol18": {"name": "Gold Gram", "price": 2674638}, "ounce": {"name": "Ounce", "price": 2040.25}, "bitcoin": {"name": "Bitcoin", "price": 42949.18}}
