{"USD": {"name": "US Dollar", "sell": 61200, "buy": 61100}, "EUR": {"name": "Euro", "sell": 65900, "buy": 65800}, "GBP": {"name": "British Pound", "sell": 76800, "buy": 76600}, "CHF": {"name": "Swiss Franc", "sell": 67600, "buy": 67500}, "CAD": {"name": "Canadian Dollar", "sell": 44750, "buy": 44650}, "AUD": {"name": "Australian Dollar", "sell": 40400, "buy": 40300}, "SEK": {"name": "Swedish Krona", "sell": 5675, "buy": 5660}, "NOK": {"name": "Norwegian Krone", "sell": 5620, "buy": 5605}, "RUB": {"name": "Russian Ruble", "sell": 670, "buy": 665}, "THB": {"name": "Thai Baht", "sell": 1660, "buy": 1655}, "SGD": {"name": "Singapore Dollar", "sell": 45350, "buy": 45250}, "HKD": {"name": "Hong Kong Dollar", "sell": 7835, "buy": 7805}, "AZN": {"name": "Azerbaijani Manat", "sell": 35900, "buy": 35800}, "AMD": {"name": "10 Armenian Dram", "sell": 1580, "buy": 1575}, "DKK": {"name": "Danish Krone", "sell": 8830, "buy": 8810}, "AED": {"name": "UAE Dirham", "sell": 16680, "buy": 16640}, "JPY": {"name": "10 Japanese Yen", "sell": 4000, "buy": 3990}, "TRY": {"name": "Turkish Lira", "sell": 1890, "buy": 1870}, "CNY": {"name": "Chinese Yuan", "sell": 8455, "buy": 8435}, "SAR": {"name": "Saudi Riyal", "sell": 16300, "buy": 16200}, "INR": {"name": "Indian Rupee", "sell": 735, "buy": 730}, "MYR": {"name": "Malaysian Ringgit", "sell": 12900, "buy": 12800}, "AFN": {"name": "Afghan Afghani", "sell": 850, "buy": 845}, "KWD": {"name": "Kuwaiti Dinar", "sell": 199100, "buy": 198700}, "IQD": {"name": "100 Iraqi Dinar", "sell": 4685, "buy": 4675}, "BHD": {"name": "Bahraini Dinar", "sell": 162500, "buy": 162000}, "OMR": {"name": "Omani Rial", "sell": 159200, "buy": 158900}, "QAR": {"name": "Qatari Rial", "sell": 16800, "buy": 16700}, "emami1": {"name": "Emami", "sell": 41400000, "buy": 40600000}, "azadi1g": {"name": "Gerami", "sell": 6500000, "buy": 6100000}, "azadi1": {"name": "Azadi", "sell": 38000000, "buy": 37200000}, "azadi1_2": {"name": "½ Azadi", "sell": 23900000, "buy": 23300000}, "azadi1_4": {"name": "¼ Azadi", "sell": 15200000, "buy": 14500000}, "mithqal": {"name": "Gold Mithqal", "price": 14719000}, "gol18": {"name": "Gold Gram", "price": 3397894}, "ounce": {"name": "Ounce", "price": 2302.57}, "bitcoin": {"name": "Bitcoin", "price": 63679.48}}
