{"USD": {"name": "US Dollar", "sell": 60400, "buy": 60300}, "EUR": {"name": "Euro", "sell": 65500, "buy": 65400}, "GBP": {"name": "British Pound", "sell": 76550, "buy": 76350}, "CHF": {"name": "Swiss Franc", "sell": 68200, "buy": 68100}, "CAD": {"name": "Canadian Dollar", "sell": 44400, "buy": 44300}, "AUD": {"name": "Australian Dollar", "sell": 39150, "buy": 39050}, "SEK": {"name": "Swedish Krona", "sell": 5810, "buy": 5795}, "NOK": {"name": "Norwegian Krone", "sell": 5700, "buy": 5685}, "RUB": {"name": "Russian Ruble", "sell": 660, "buy": 655}, "THB": {"name": "Thai Baht", "sell": 1685, "buy": 1680}, "SGD": {"name": "Singapore Dollar", "sell": 44950, "buy": 44850}, "HKD": {"name": "Hong Kong Dollar", "sell": 7720, "buy": 7690}, "AZN": {"name": "Azerbaijani Manat", "sell": 35400, "buy": 35300}, "AMD": {"name": "10 Armenian Dram", "sell": 1495, "buy": 1490}, "DKK": {"name": "Danish Krone", "sell": 8790, "buy": 8770}, "AED": {"name": "UAE Dirham", "sell": 16370, "buy": 16320}, "JPY": {"name": "10 Japanese Yen", "sell": 4015, "buy": 4005}, "TRY": {"name": "Turkish Lira", "sell": 1910, "buy": 1890}, "CNY": {"name": "Chinese Yuan", "sell": 8390, "buy": 8370}, "SAR": {"name": "Saudi Riyal", "sell": 16100, "buy": 16000}, "INR": {"name": "Indian Rupee", "sell": 730, "buy": 725}, "MYR": {"name": "Malaysian Ringgit", "sell": 12750, "buy": 12650}, "AFN": {"name": "Afghan Afghani", "sell": 820, "buy": 815}, "KWD": {"name": "Kuwaiti Dinar", "sell": 196350, "buy": 195950}, "IQD": {"name": "100 Iraqi Dinar", "sell": 4605, "buy": 4595}, "BHD": {"name": "Bahraini Dinar", "sell": 160300, "buy": 159800}, "OMR": {"name": "Omani Rial", "sell": 156900, "buy": 156600}, "QAR": {"name": "Qatari Rial", "sell": 16600, "buy": 16500}, "emami1": {"name": "Emami", "sell": 36150000, "buy": 35800000}, "azadi1g": {"name": "Gerami", "sell": 6400000, "buy": 6150000}, "azadi1": {"name": "Azadi", "sell": 33900000, "buy": 33300000}, "azadi1_2": {"name": "½ Azadi", "sell": 20000000, "buy": 19700000}, "azadi1_4": {"name": "¼ Azadi", "sell": 12950000, "buy": 12600000}, "mithqal": {"name": "Gold Mithqal", "price": 13411000}, "gol18": {"name": "Gold Gram", "price": 3095941}, "ounce": {"name": "Ounce", "price": 2119.3}, "bitcoin": {"name": "Bitcoin", "price": 66590.5}}
