{"USD": {"name": "US Dollar", "sell": 59500, "buy": 59400}, "EUR": {"name": "Euro", "sell": 64350, "buy": 64250}, "GBP": {"name": "British Pound", "sell": 75550, "buy": 75350}, "CHF": {"name": "Swiss Franc", "sell": 66250, "buy": 66150}, "CAD": {"name": "Canadian Dollar", "sell": 43200, "buy": 43100}, "AUD": {"name": "Australian Dollar", "sell": 39250, "buy": 39150}, "SEK": {"name": "Swedish Krona", "sell": 5620, "buy": 5605}, "NOK": {"name": "Norwegian Krone", "sell": 5555, "buy": 5540}, "RUB": {"name": "Russian Ruble", "sell": 665, "buy": 660}, "THB": {"name": "Thai Baht", "sell": 1615, "buy": 1610}, "SGD": {"name": "Singapore Dollar", "sell": 44050, "buy": 43950}, "HKD": {"name": "Hong Kong Dollar", "sell": 7615, "buy": 7585}, "AZN": {"name": "Azerbaijani Manat", "sell": 34900, "buy": 34800}, "AMD": {"name": "10 Armenian Dram", "sell": 1525, "buy": 1520}, "DKK": {"name": "Danish Krone", "sell": 8610, "buy": 8590}, "AED": {"name": "UAE Dirham", "sell": 16160, "buy": 16120}, "JPY": {"name": "10 Japanese Yen", "sell": 3795, "buy": 3785}, "TRY": {"name": "Turkish Lira", "sell": 1835, "buy": 1815}, "CNY": {"name": "Chinese Yuan", "sell": 8210, "buy": 8190}, "SAR": {"name": "Saudi Riyal", "sell": 15850, "buy": 15750}, "INR": {"name": "Indian Rupee", "sell": 710, "buy": 705}, "MYR": {"name": "Malaysian Ringgit", "sell": 12700, "buy": 12600}, "AFN": {"name": "Afghan Afghani", "sell": 840, "buy": 835}, "KWD": {"name": "Kuwaiti Dinar", "sell": 194050, "buy": 193650}, "IQD": {"name": "100 Iraqi Dinar", "sell": 4510, "buy": 4500}, "BHD": {"name": "Bahraini Dinar", "sell": 157850, "buy": 157350}, "OMR": {"name": "Omani Rial", "sell": 154550, "buy": 154250}, "QAR": {"name": "Qatari Rial", "sell": 16200, "buy": 16100}, "emami1": {"name": "Emami", "sell": 40500000, "buy": 40150000}, "azadi1g": {"name": "Gerami", "sell": 6900000, "buy": 6500000}, "azadi1": {"name": "Azadi", "sell": 37600000, "buy": 37000000}, "azadi1_2": {"name": "½ Azadi", "sell": 23200000, "buy": 22800000}, "azadi1_4": {"name": "¼ Azadi", "sell": 15000000, "buy": 14600000}, "mithqal": {"name": "Gold Mithqal", "price": 14369000}, "gol18": {"name": "Gold Gram", "price": 3317096}, "ounce": {"name": "Ounce", "price": 2293.84}, "bitcoin": {"name": "Bitcoin", "price": 69367.86}}
