{"USD": {"name": "US Dollar", "sell": 61450, "buy": 61350}, "EUR": {"name": "Euro", "sell": 66200, "buy": 66100}, "GBP": {"name": "British Pound", "sell": 77100, "buy": 76900}, "CHF": {"name": "Swiss Franc", "sell": 67900, "buy": 67800}, "CAD": {"name": "Canadian Dollar", "sell": 44900, "buy": 44800}, "AUD": {"name": "Australian Dollar", "sell": 40650, "buy": 40550}, "SEK": {"name": "Swedish Krona", "sell": 5690, "buy": 5675}, "NOK": {"name": "Norwegian Krone", "sell": 5665, "buy": 5650}, "RUB": {"name": "Russian Ruble", "sell": 660, "buy": 655}, "THB": {"name": "Thai Baht", "sell": 1670, "buy": 1665}, "SGD": {"name": "Singapore Dollar", "sell": 45550, "buy": 45450}, "HKD": {"name": "Hong Kong Dollar", "sell": 7865, "buy": 7835}, "AZN": {"name": "Azerbaijani Manat", "sell": 36250, "buy": 36150}, "AMD": {"name": "10 Armenian Dram", "sell": 1585, "buy": 1580}, "DKK": {"name": "Danish Krone", "sell": 8875, "buy": 8855}, "AED": {"name": "UAE Dirham", "sell": 16920, "buy": 16880}, "JPY": {"name": "10 Japanese Yen", "sell": 4020, "buy": 4010}, "TRY": {"name": "Turkish Lira", "sell": 1900, "buy": 1880}, "CNY": {"name": "Chinese Yuan", "sell": 8490, "buy": 8470}, "SAR": {"name": "Saudi Riyal", "sell": 16400, "buy": 16300}, "INR": {"name": "Indian Rupee", "sell": 735, "buy": 730}, "MYR": {"name": "Malaysian Ringgit", "sell": 12950, "buy": 12850}, "AFN": {"name": "Afghan Afghani", "sell": 850, "buy": 845}, "KWD": {"name": "Kuwaiti Dinar", "sell": 199950, "buy": 199550}, "IQD": {"name": "100 Iraqi Dinar", "sell": 4690, "buy": 4680}, "BHD": {"name": "Bahraini Dinar", "sell": 163000, "buy": 162500}, "OMR": {"name": "Omani Rial", "sell": 159650, "buy": 159350}, "QAR": {"name": "Qatari Rial", "sell": 16900, "buy": 16800}, "emami1": {"name": "Emami", "sell": 41800000, "buy": 41300000}, "azadi1g": {"name": "Gerami", "sell": 6700000, "buy": 6200000}, "azadi1": {"name": "Azadi", "sell": 38200000, "buy": 37500000}, "azadi1_2": {"name": "½ Azadi", "sell": 24200000, "buy": 23700000}, "azadi1_4": {"name": "¼ Azadi", "sell": 15500000, "buy": 15000000}, "mithqal": {"name": "Gold Mithqal", "price": 14790000}, "gol18": {"name": "Gold Gram", "price": 3414285}, "ounce": {"name": "Ounce", "price": 2298.02}, "bitcoin": {"name": "Bitcoin", "price": 61993.79}}
